transcriptorthology/Tclustering.py
transcriptorthology/__init__.py
transcriptorthology/transcriptOrthology.py
transcriptorthology/tsmComputing.py
transcriptorthology-3.0.2.dist-info/METADATA
transcriptorthology-3.0.2.dist-info/WHEEL
transcriptorthology-3.0.2.dist-info/top_level.txt
transcriptorthology-3.0.2.dist-info/RECORD
