Metadata-Version: 2.1
Name: transcriptorthology
Version: 3.0.2
Summary: Algorithm to address Orthology and Paralogy at the Transcript Level
Home-page: https://github.com/UdeS-CoBIUS/TranscriptOrthology
Author: Wend Yam Donald Davy Ouedraogo
Author-email: wend.yam.donald.davy.ouedraogo@usherbrooke.ca
License: CoBIUS Lab
Keywords: clustering,alternative splicing,orthology-paralogy inference,isoorthology,algorithm,evolution,transcripts,phylogeny,computational-biology
Platform: UNKNOWN
Classifier: Development Status :: 3 - Alpha
Classifier: Intended Audience :: Developers
Classifier: License :: OSI Approved :: MIT License
Classifier: Programming Language :: Python :: 3
Requires-Dist: pandas
Requires-Dist: ete3
Requires-Dist: networkx
Requires-Dist: matplotlib
Requires-Dist: argparse
Requires-Dist: numpy
